{
  "colorScheme": "light",
  "variables": {
    "--bg": "#f9f5ec",
    "--surface": "#f4eee1",
    "--surface-2": "#efe8d7",
    "--surface-3": "#e8dfc9",
    "--border": "#d7cab2",
    "--border-soft": "#e4dac3",
    "--text": "#252018",
    "--muted": "#665c47",
    "--faint": "#a6936e",
    "--accent": "#553a0c",
    "--accent-bright": "#432e0a",
    "--accent-deep": "#b2482e",
    "--danger": "#a34d38",
    "--shadow-large": "#ffffffcc",
    "--shadow-medium": "#ffffffbb",
    "--shadow-modal": "#ffffffdd",
    "--shadow-small": "#ffffff99",
    "--shadow-dropdown": "#ffffffaa",
    "--shadow-overlay": "#ffffffee",
    "--shadow-tooltip": "#ffffff77",
    "--shadow-subtle": "#ffffff33"
  }
}
